dashbar/__init__.py
dashbar/_dashBuilder.py
dashbar/_dashbarElements.py
dashbar/demo.py
dashbar/exceptions.py
dashbar-2.1.dist-info/LICENSE
dashbar-2.1.dist-info/METADATA
dashbar-2.1.dist-info/WHEEL
dashbar-2.1.dist-info/top_level.txt
dashbar-2.1.dist-info/RECORD
