Metadata-Version: 2.1
Name: dashbar
Version: 2.1
Summary: A progress-bar designed to be useful and easy to use.
Home-page: https://github.com/xyzpw/dashbar/
Author: xyzpw
Maintainer: xyzpw
License: MIT
Classifier: Operating System :: POSIX :: Linux
Classifier: Topic :: Utilities
Classifier: Intended Audience :: Developers
Classifier: Programming Language :: Python :: 3
Classifier: Programming Language :: Python :: 3.7
Classifier: Programming Language :: Python :: 3.8
Classifier: Programming Language :: Python :: 3.9
Classifier: Programming Language :: Python :: 3.10
Classifier: Programming Language :: Python :: 3.11
Classifier: Programming Language :: Python :: 3.12
Classifier: Environment :: Console :: Curses
Classifier: Environment :: Console
Requires-Python: >=3.7
License-File: LICENSE
